nbgrader_server-0.1.data/scripts/server.py
nbgrader_server-0.1.dist-info/METADATA
nbgrader_server-0.1.dist-info/RECORD
nbgrader_server-0.1.dist-info/WHEEL
nbgrader_server-0.1.dist-info/top_level.txt
nbgraderapi/__init__.py
nbgraderapi/assignment.py
nbgraderapi/auth.py
nbgraderapi/handlers.py
