Metadata-Version: 2.1
Name: nbgrader-server
Version: 0.1
Summary: API server for nbgrader
Home-page: https://github.com/kidig/nbgrader-server
Author: Dmitry Gerasimenko
Author-email: kiddima@gmail.com
License: BSD
Keywords: jupyter-notebook,nbgrader,tornado
Platform: UNKNOWN
Classifier: License :: OSI Approved :: BSD License
Classifier: Programming Language :: Python
Classifier: Development Status :: 3 - Alpha
Requires-Dist: tornado (>=5.1)
Requires-Dist: nbgrader (>=0.5)
